{
  "date": "2026-05-25",
  "price_ctx": {
    "price": 745.6400146484375,
    "ret_12m": 0.2934326711926949,
    "extension_200d": 0.10261192882292836,
    "drawdown": -0.003381542055293285,
    "sma_200": 676.2488189697266,
    "high_52w": 748.1699829101562,
    "regime_label": "Extended uptrend, stretched above trend",
    "days_since_5pct": 35,
    "days_since_10pct": 271
  },
  "h_scores": {
    "5d": 17.319360031985617,
    "21d": 24.7441741264476,
    "63d": 40.19452025737362
  },
  "signals": {
    "Distribution Dominance": {
      "on": false,
      "detail": "",
      "summary": "D/A ratio: 1.0 (threshold: 3.75) \u2014 4D / 4A last 63d"
    },
    "VIX Range Compression": {
      "on": false,
      "detail": "",
      "summary": "21d range: 3th pctile (fires below 15th) \u2014 VIX at 16.6"
    },
    "Defensive Leadership": {
      "on": false,
      "detail": "",
      "summary": "50d spread: +16pp (fires < -10) | 200d spread: +3pp (fires < 0)"
    },
    "Pre-FOMC Rally": {
      "on": false,
      "detail": "",
      "summary": "Next FOMC: Jun 17 (26d away) \u2014 5d return: 60th pctile (outside window)"
    },
    "Low Absorption Ratio": {
      "on": false,
      "detail": "",
      "summary": "AR: 0.460 (41th pctile, fires below 10th) \u2014 near high: yes"
    },
    "Seasonal Rank Divergence": {
      "on": false,
      "detail": "",
      "summary": "Spread: +6.8pp (fires above 10) \u2014 near high: yes"
    },
    "Dispersion": {
      "on": false,
      "detail": "",
      "summary": "Composite pctile: 96th (fires above 85th) \u2014 component RV: 35.4% | SPY RV: 10.2%"
    }
  }
}